lingkaran/__init__.py
lingkaran/luas_lingkaran.py
lingkar33423314-0.0.1.dist-info/LICENSE.txt
lingkar33423314-0.0.1.dist-info/METADATA
lingkar33423314-0.0.1.dist-info/WHEEL
lingkar33423314-0.0.1.dist-info/top_level.txt
lingkar33423314-0.0.1.dist-info/RECORD
