Metadata-Version: 2.1
Name: lingkar33423314
Version: 0.0.1
Summary: Library Python sederhana untuk menghitung luas lingkaran.
Home-page: 
Author: Hassan
Author-email: <mhnzayyan@gmail.com>
License: MIT
Keywords: luas,lingkaran
Classifier: Development Status :: 1 - Planning
License-File: LICENSE.txt
